seashells/__init__.py
seashells_sc-0.1.6.dist-info/DESCRIPTION.rst
seashells_sc-0.1.6.dist-info/METADATA
seashells_sc-0.1.6.dist-info/RECORD
seashells_sc-0.1.6.dist-info/WHEEL
seashells_sc-0.1.6.dist-info/entry_points.txt
seashells_sc-0.1.6.dist-info/metadata.json
seashells_sc-0.1.6.dist-info/top_level.txt
